README.rst
setup.py
flask_github_proxy/__init__.py
flask_github_proxy/models.py
flask_github_proxy.egg-info/PKG-INFO
flask_github_proxy.egg-info/SOURCES.txt
flask_github_proxy.egg-info/dependency_links.txt
flask_github_proxy.egg-info/not-zip-safe
flask_github_proxy.egg-info/requires.txt
flask_github_proxy.egg-info/top_level.txt